gitlabracadabra/__init__.py
gitlabracadabra/auth_info.py
gitlabracadabra/cli.py
gitlabracadabra/dictutils.py
gitlabracadabra/disk_cache.py
gitlabracadabra/matchers.py
gitlabracadabra/parser.py
gitlabracadabra/session.py
gitlabracadabra/singleton.py
gitlabracadabra/containers/__init__.py
gitlabracadabra/containers/authenticated_session.py
gitlabracadabra/containers/blob.py
gitlabracadabra/containers/const.py
gitlabracadabra/containers/manifest.py
gitlabracadabra/containers/manifest_base.py
gitlabracadabra/containers/registries.py
gitlabracadabra/containers/registry.py
gitlabracadabra/containers/registry_importer.py
gitlabracadabra/containers/registry_session.py
gitlabracadabra/containers/scope.py
gitlabracadabra/containers/with_blobs.py
gitlabracadabra/containers/with_digest.py
gitlabracadabra/gitlab/__init__.py
gitlabracadabra/gitlab/access_levels.py
gitlabracadabra/gitlab/connection.py
gitlabracadabra/gitlab/connections.py
gitlabracadabra/gitlab/deploy_key_cache.py
gitlabracadabra/gitlab/group_cache.py
gitlabracadabra/gitlab/pygit2.py
gitlabracadabra/gitlab/pygitlab.py
gitlabracadabra/gitlab/user_cache.py
gitlabracadabra/mixins/__init__.py
gitlabracadabra/mixins/boards.py
gitlabracadabra/mixins/groups.py
gitlabracadabra/mixins/image_mirrors.py
gitlabracadabra/mixins/labels.py
gitlabracadabra/mixins/members.py
gitlabracadabra/mixins/milestones.py
gitlabracadabra/mixins/mirrors.py
gitlabracadabra/mixins/package_mirrors.py
gitlabracadabra/mixins/pipeline_schedules.py
gitlabracadabra/mixins/protected_branches.py
gitlabracadabra/mixins/rename_branches.py
gitlabracadabra/mixins/variables.py
gitlabracadabra/mixins/webhooks.py
gitlabracadabra/objects/__init__.py
gitlabracadabra/objects/application_settings.py
gitlabracadabra/objects/group.py
gitlabracadabra/objects/object.py
gitlabracadabra/objects/project.py
gitlabracadabra/objects/user.py
gitlabracadabra/packages/__init__.py
gitlabracadabra/packages/destination.py
gitlabracadabra/packages/github.py
gitlabracadabra-2.7.1.dist-info/METADATA
gitlabracadabra-2.7.1.dist-info/WHEEL
gitlabracadabra-2.7.1.dist-info/entry_points.txt
gitlabracadabra-2.7.1.dist-info/licenses/LICENSE
gitlabracadabra-2.7.1.dist-info/RECORD
