Metadata-Version: 2.4
Name: gitlabracadabra
Version: 2.7.1
Summary: Adds some magic to GitLab
Project-URL: Homepage, https://gitlab.com/gitlabracadabra/gitlabracadabra
Project-URL: Issues, https://gitlab.com/gitlabracadabra/gitlabracadabra/-/issues
Project-URL: Source, https://gitlab.com/gitlabracadabra/gitlabracadabra
Author-email: Mathieu Parent <math.parent@gmail.com>
License-Expression: LGPL-3.0-or-later
License-File: LICENSE
Keywords: api,gitlab,yaml
Classifier: Development Status :: 5 - Production/Stable
Classifier: Environment :: Console
Classifier: Intended Audience :: System Administrators
Classifier: License :: OSI Approved :: GNU Lesser General Public License v3 (LGPLv3)
Classifier: Natural Language :: English
Classifier: Operating System :: Microsoft :: Windows
Classifier: Operating System :: POSIX
Classifier: Programming Language :: Python
Classifier: Programming Language :: Python :: 3.11
Classifier: Programming Language :: Python :: 3.12
Requires-Python: >=3.11
Requires-Dist: html5lib-modern
Requires-Dist: jsonschema>=2.6.0
Requires-Dist: packaging
Requires-Dist: pip-system-certs
Requires-Dist: pygit2
Requires-Dist: pygithub
Requires-Dist: python-gitlab>=2.5.0
Requires-Dist: pyyaml
Requires-Dist: semantic-version
